{
  "typography": {
    "displayName": "Tipografía",
    "properties": {
      "applyTo": {
        "displayName": "Aplicar a",
        "type": {
          "enumeration": [
            {
              "value": "all",
              "displayName": "Toda la tabla"
            },
            {
              "value": "column",
              "displayName": "Columna específica"
            }
          ]
        }
      },
      "targetColumn": {
        "displayName": "Columna objetivo",
        "type": {
          "enumeration": []
        }
      },
      "fontFamily": {
        "displayName": "Familia de fuente",
        "type": {
          "enumeration": [
            {
              "value": "Arial, sans-serif",
              "displayName": "Arial"
            },
            {
              "value": "Verdana, sans-serif",
              "displayName": "Verdana"
            },
            {
              "value": "Georgia, serif",
              "displayName": "Georgia"
            },
            {
              "value": "'Courier New', monospace",
              "displayName": "Courier New"
            },
            {
              "value": "'Segoe UI', sans-serif",
              "displayName": "Segoe UI"
            },
            {
              "value": "Tahoma, sans-serif",
              "displayName": "Tahoma"
            },
            {
              "value": "'Times New Roman', serif",
              "displayName": "Times New Roman"
            }
          ]
        }
      },
      "fontSize": {
        "displayName": "Tamaño",
        "type": {
          "numeric": true
        }
      },
      "bold": {
        "displayName": "Negrita",
        "type": {
          "bool": true
        }
      },
      "italic": {
        "displayName": "Cursiva",
        "type": {
          "bool": true
        }
      },
      "underline": {
        "displayName": "Subrayado",
        "type": {
          "bool": true
        }
      },
      "fontColor": {
        "displayName": "Color de texto",
        "type": {
          "fill": {
            "solid": {
              "color": true
            }
          }
        }
      },
      "alignment": {
        "displayName": "Alineación",
        "type": {
          "enumeration": [
            {
              "value": "left",
              "displayName": "Izquierda"
            },
            {
              "value": "center",
              "displayName": "Centro"
            },
            {
              "value": "right",
              "displayName": "Derecha"
            }
          ]
        }
      },
      "lineHeight": {
        "displayName": "Alto de línea",
        "type": {
          "numeric": true
        }
      },
      "letterSpacing": {
        "displayName": "Espaciado entre letras",
        "type": {
          "numeric": true
        }
      }
    }
  }
}